modshib/__init__.py
modshib/admin.py
modshib/apps.py
modshib/context_processors.py
modshib/migrations/__init__.py
modshib/models.py
modshib/static/modshib/bootstrap.min.css
modshib/static/modshib/bootstrap.min.css.map
modshib/templates/registration/logged_out.html
modshib/templates/registration/login.html
modshib/templates/registration/reg_base.html
modshib/templates/registration/sso_fail.html
modshib/templates/registration/sso_no_account.html
modshib/tests.py
modshib/urls.py
modshib/views.py
django_modshib_certic-0.2.7.dist-info/LICENSE.txt
django_modshib_certic-0.2.7.dist-info/METADATA
django_modshib_certic-0.2.7.dist-info/WHEEL
django_modshib_certic-0.2.7.dist-info/RECORD
