Metadata-Version: 2.1
Name: django-modshib-CERTIC
Version: 0.2.7
Summary: Faciliter la gestion de l'authentification avec le module Apache mod_shib depuis Django
Home-page: https://www.certic.unicaen.fr
License: LICENSE.txt
Author: Mickaël Desfrênes
Author-email: mickael.desfrenes@unicaen.fr
Requires-Python: >=3.9,<4.0
Classifier: License :: Other/Proprietary License
Classifier: Programming Language :: Python :: 3
Classifier: Programming Language :: Python :: 3.9
Classifier: Programming Language :: Python :: 3.10
Classifier: Programming Language :: Python :: 3.11
Classifier: Programming Language :: Python :: 3.12
Requires-Dist: Django (>=4.0)
Requires-Dist: django-auth-cli-certic (>=0.1.3)
Project-URL: Repository, https://git.unicaen.fr/certic/django-modshib
